AOCRla/__init__.py
AOCRla/aoc.py
aocrla-0.1.0.dist-info/METADATA
aocrla-0.1.0.dist-info/WHEEL
aocrla-0.1.0.dist-info/licenses/LICENSE
aocrla-0.1.0.dist-info/RECORD
