Metadata-Version: 2.1
Name: AOCRla
Version: 0.1.0
Summary: A simple package to help with Advent of Code input downloads and result posting.
Project-URL: Homepage, https://github.com/tonyrla/AOCUtil
Author-email: Tony Rintala <rintala.tony@gmail.com>
License-File: LICENSE
Classifier: License :: OSI Approved :: MIT License
Classifier: Operating System :: OS Independent
Classifier: Programming Language :: Python :: 3
Requires-Python: >=3.11
Requires-Dist: requests==2.28.1
